rbxmppnotification/__init__.py
rbxmppnotification/admin_urls.py
rbxmppnotification/extension.py
rbxmppnotification/forms.py
rbxmppnotification/register.py
rbxmppnotification/views.py
rbxmppnotification/xmpp.py
rbxmppnotification/templates/rbxmppnotification/configure.html
RBXmppNotification-0.5.0.dist-info/top_level.txt
RBXmppNotification-0.5.0.dist-info/entry_points.txt
RBXmppNotification-0.5.0.dist-info/METADATA
RBXmppNotification-0.5.0.dist-info/DESCRIPTION.rst
RBXmppNotification-0.5.0.dist-info/metadata.json
RBXmppNotification-0.5.0.dist-info/WHEEL
RBXmppNotification-0.5.0.dist-info/RECORD
