Metadata-Version: 2.0
Name: RBXmppNotification
Version: 0.5.0
Summary: ReviewBoard XMPP Notification Extension
Home-page: https://github.com/iconoeugen/rb-xmpp-notification
Author: Horatiu Eugen Vlad
Author-email: horatiuvlad[at]yahoo.com
License: MIT
Keywords: xmpp development review reviewboard
Platform: UNKNOWN
Requires-Dist: pyxmpp2 (>=2.0alpha2)
Requires-Dist: argparse (>=1.2)
